README.rst
setup.py
YamJam/__init__.py
YamJam/yjlint.py
yamjam.egg-info/PKG-INFO
yamjam.egg-info/SOURCES.txt
yamjam.egg-info/dependency_links.txt
yamjam.egg-info/entry_points.txt
yamjam.egg-info/requires.txt
yamjam.egg-info/top_level.txt