Metadata-Version: 1.1
Name: yamjam
Version: 0.1.7
Summary: A multi-project, shared, yaml based configuration system. Works with Django
Home-page: https://bitbucket.org/dundeemt/yamjam
Author: Jeff Hinrichs
Author-email: jeffh@dundeemt.com
License: BSD - LICENSE.txt
Keywords: config yaml django settings
Platform: any
Classifier: Development Status :: 4 - Beta
Classifier: License :: OSI Approved :: BSD License
Classifier: Operating System :: OS Independent
Classifier: Programming Language :: Python
Classifier: Programming Language :: Python :: 2
Classifier: Programming Language :: Python :: 2.7
Classifier: Programming Language :: Python :: 3
Classifier: Programming Language :: Python :: 3.2
Classifier: Programming Language :: Python :: 3.3
Classifier: Programming Language :: Python :: 3.4
Classifier: Programming Language :: Python :: Implementation :: CPython
Classifier: Programming Language :: Python :: Implementation :: PyPy
